{
  "cli": {
    "version": ">= 5.2.0"
  },
  "build": {
    "development": {
      "developmentClient": true,
      "distribution": "internal",
      "ios": {

      }
    },
    "development-simulator": {
      "extends":"development",
      "ios": {
        "simulator":true
      }
    },
    "preview": {
      "distribution": "internal"
    },
    "production": {}
  },
  "submit": {
    "production": {
      "ios": {
        "appleId": "sathya.venugopal2003@gmail.com",
        "ascAppId": "6468644109",
        "appleTeamId":"B7739YZ8TT"
      }
    }
  }
}
